[
    {"reportID" : 1, "name" : "Alfonso De Maio", "date" : "09/06/2021 13:30", "place" : "Nocera Inferiore (SA), Via Villanova 42", "severity" : "Basso", "contactPhone" : "+39 3331234567", "contactEmail" : "alfonsodemaio@gmail.com", "reportHome" : "Angri (SA), Via Rosa 19", "firstRow" : 3, "secondRow" : 4, "thirdRow" : 4, "fourthRow" : 4, "fifthRow" : 5, "sixthRow" : 6, "seventhRow" : 4},
    {"reportID" : 2, "name" : "Giovanni De Luca", "date" : "08/06/2021 12:39", "place" : "Angri (SA), Via Marco Polo 19", "severity" : "Medio", "contactPhone" : "+39 3312345678", "contactEmail" : "giovannideluca@gmail.com", "reportHome" : "Nocera Inferiore (SA), Via Cedro 94", "firstRow" : 4, "secondRow" : 3, "thirdRow" : 3, "fourthRow" : 4, "fifthRow" : 4, "sixthRow" : 5, "seventhRow" : 3},
    {"reportID" : 3, "name" : "Marco Pierro", "date" : "09/06/2021 17:39", "place" : "Pagani (SA), Via Trieste 40", "severity" : "Medio", "contactPhone" : "+39 3234567982", "contactEmail" : "marcopierro@gmail.com", "reportHome" : "Pagani (SA), Via Roma 1", "firstRow" : 3, "secondRow" : 2, "thirdRow" : 2, "fourthRow" : 4, "fifthRow" : 4, "sixthRow" : 5, "seventhRow" : 3},
    {"reportID" : 4, "name" : "Lorenzo Criscuolo", "date" : "07/06/2021 11:49", "place" : "Nocera Inferiore (SA), Via Roma 19", "severity" : "Medio", "contactPhone" : "+39 3333333333", "contactEmail" : "lorycriscuolo@gmail.com", "reportHome" : "Pagani (SA), Corso Matteotti 19", "firstRow" : 3, "secondRow" : 2, "thirdRow" : 2, "fourthRow" : 3, "fifthRow" : 4, "sixthRow" : 1, "seventhRow" : 3},
    {"reportID" : 5, "name" : "Miriam Martone", "date" : "31/05/2021 12:00", "place" : "Sarno (SA), Via Roma 15", "severity" : "Alto", "contactPhone" : "+39 3341234567", "contactEmail" : "miriammartone@gmail.com", "reportHome" : "Sarno (SA), Via del Campo 19", "firstRow" : 5, "secondRow" : 4, "thirdRow" : 5, "fourthRow" : 5, "fifthRow" : 6, "sixthRow" : 5, "seventhRow" : 5},
    {"reportID" : 6, "name" : "Hermann Senatore", "date" : "05/06/2021 9:41", "place" : "Nocera Inferiore (SA), Via Basso 19", "severity" : "Alto", "contactPhone" : "+39 3331234567", "contactEmail" : "h.senatore@gmail.com", "reportHome" : "Nocera Inferiore (SA), Via dei Pini 15", "firstRow" : 4, "secondRow" : 4, "thirdRow" : 5, "fourthRow" : 4, "fifthRow" : 4, "sixthRow" : 5, "seventhRow" : 3}
]